Workbook

Sheet Scenario
A1: Variable | B1: Bull | C1: Base | D1: Bear | F1: Select Scenario | H1: Active Assumptions | I1: Metrics
A2: RevenueGrowth | B2: 0.35 | C2: 0.2 | D2: 0.1 | F2: Base | H2: RevenueGrowth | I2: =IF($F$2="Bull", B2, IF($F$2="Base", C2, IF($F$2="Bear", D2, ""))) -> 0.2
A3: COGS_%OfRev | B3: 0.35 | C3: 0.4 | D3: 0.5 | H3: COGS_%OfRev | I3: =IF($F$2="Bull", B3, IF($F$2="Base", C3, IF($F$2="Bear", D3, ""))) -> 0.4
A4: Opex_%OfRev | B4: 0.45 | C4: 0.5 | D4: 0.6 | H4: Opex_%OfRev | I4: =IF($F$2="Bull", B4, IF($F$2="Base", C4, IF($F$2="Bear", D4, ""))) -> 0.5
A5: Tax % | B5: 0.21 | C5: 0.21 | D5: 0.21 | H5: Tax % | I5: =IF($F$2="Bull", B5, IF($F$2="Base", C5, IF($F$2="Bear", D5, ""))) -> 0.21
A6: CapEx | B6: -500000 | C6: -500000 | D6: -500000 | H6: CapEx | I6: =IF($F$2="Bull", B6, IF($F$2="Base", C6, IF($F$2="Bear", D6, ""))) -> -500000

Sheet Assumptions
A1: Start Revenue (Year 1) | B1: 5000000
A2: RevenueGrowth | B2: =Scenario!I2 -> 0.2
A3: COGS_%OfRev | B3: =Scenario!I3 -> 0.4
A4: Opex_%OfRev | B4: =Scenario!I4 -> 0.5
A5: Tax % | B5: =Scenario!I5 -> 0.21
A6: Starting cash | B6: 0
A7: Starting PPE | B7: 2000000
A8: Starting equity | B8: 2000000
A9: CapEx | B9: =Scenario!I6 -> -500000

Sheet PL
A1: Year | B1: Revenue | C1: COGS | D1: GrossProfit | E1: Opex | F1: EBIT | G1: Taxes | H1: NetIncome
A2: 2026 | B2: =Assumptions!$B$1*(1+Assumptions!$B$2) -> 6000000 | C2: =B2*Assumptions!$B$3 -> 2400000 | D2: =B2-C2 -> 3600000 | E2: =B2*Assumptions!$B$4 -> 3000000 | F2: =D2-E2 -> 600000 | G2: =F2*Assumptions!$B$5 -> 126000 | H2: =F2-G2 -> 474000
A3: 2027 | B3: =B2*(1+Assumptions!$B$2) -> 7200000 | C3: =B3*Assumptions!$B$3 -> 2880000 | D3: =B3-C3 -> 4320000 | E3: =B3*Assumptions!$B$4 -> 3600000 | F3: =D3-E3 -> 720000 | G3: =F3*Assumptions!$B$5 -> 151200 | H3: =F3-G3 -> 568800
A4: 2028 | B4: =B3*(1+Assumptions!$B$2) -> 8640000 | C4: =B4*Assumptions!$B$3 -> 3456000 | D4: =B4-C4 -> 5184000 | E4: =B4*Assumptions!$B$4 -> 4320000 | F4: =D4-E4 -> 864000 | G4: =F4*Assumptions!$B$5 -> 181440 | H4: =F4-G4 -> 682560
A5: 2029 | B5: =B4*(1+Assumptions!$B$2) -> 10368000 | C5: =B5*Assumptions!$B$3 -> 4147200 | D5: =B5-C5 -> 6220800 | E5: =B5*Assumptions!$B$4 -> 5184000 | F5: =D5-E5 -> 1036800 | G5: =F5*Assumptions!$B$5 -> 217728 | H5: =F5-G5 -> 819072
A6: 2030 | B6: =B5*(1+Assumptions!$B$2) -> 12441600 | C6: =B6*Assumptions!$B$3 -> 4976640 | D6: =B6-C6 -> 7464960 | E6: =B6*Assumptions!$B$4 -> 6220800 | F6: =D6-E6 -> 1244160 | G6: =F6*Assumptions!$B$5 -> 261273.6 | H6: =F6-G6 -> 982886.4

Sheet CashFlow
A1: Year | B1: NetIncome | C1: Capex | D1: FreeCashFlow | E1: EndingCash
A2: 2026 | B2: =PL!H2 -> 474000 | C2: =Assumptions!$B$9 -> -500000 | D2: =B2+C2 -> -26000 | E2: =D2 -> -26000
A3: 2027 | B3: =PL!H3 -> 568800 | C3: =Assumptions!$B$9 -> -500000 | D3: =B3+C3 -> 68800 | E3: =E2+D3 -> 42800
A4: 2028 | B4: =PL!H4 -> 682560 | C4: =Assumptions!$B$9 -> -500000 | D4: =B4+C4 -> 182560 | E4: =E3+D4 -> 225360
A5: 2029 | B5: =PL!H5 -> 819072 | C5: =Assumptions!$B$9 -> -500000 | D5: =B5+C5 -> 319072 | E5: =E4+D5 -> 544432
A6: 2030 | B6: =PL!H6 -> 982886.4 | C6: =Assumptions!$B$9 -> -500000 | D6: =B6+C6 -> 482886.4 | E6: =E5+D6 -> 1027318.4

Sheet BalanceSheet
A1: Year | B1: Cash | C1: PPE | D1: Equity | E1: Liability
A2: 2026 | B2: =CashFlow!D2 -> -26000 | C2: =Assumptions!$B$7 -> 2000000 | D2: =B2+C2 -> 1974000 | E2: 0
A3: 2027 | B3: =CashFlow!D3 -> 68800 | C3: =Assumptions!$B$7 -> 2000000 | D3: =B3+C3 -> 2068800 | E3: 0
A4: 2028 | B4: =CashFlow!D4 -> 182560 | C4: =Assumptions!$B$7 -> 2000000 | D4: =B4+C4 -> 2182560 | E4: 0
A5: 2029 | B5: =CashFlow!D5 -> 319072 | C5: =Assumptions!$B$7 -> 2000000 | D5: =B5+C5 -> 2319072 | E5: 0
A6: 2030 | B6: =CashFlow!D6 -> 482886.4 | C6: =Assumptions!$B$7 -> 2000000 | D6: =B6+C6 -> 2482886.4 | E6: 0
